groundsupport/__init__.py
groundsupport/main.py
groundsupport-1.1.1.dist-info/LICENSE
groundsupport-1.1.1.dist-info/METADATA
groundsupport-1.1.1.dist-info/WHEEL
groundsupport-1.1.1.dist-info/entry_points.txt
groundsupport-1.1.1.dist-info/RECORD
