Metadata-Version: 2.1
Name: groundsupport
Version: 1.1.1
Summary: Ground Support helps accomplish tasks in the command line.
License: The Unlicence
Author: Luís Miranda
Author-email: luistm@gmail.com
Requires-Python: >=3.9,<4.0
Classifier: License :: Other/Proprietary License
Classifier: Programming Language :: Python :: 3
Classifier: Programming Language :: Python :: 3.9
Classifier: Programming Language :: Python :: 3.10
Classifier: Programming Language :: Python :: 3.11
Classifier: Programming Language :: Python :: 3.12
Requires-Dist: awesome-slugify (>=1.6.5,<2.0.0)
Requires-Dist: turbofan (>=0.2.0,<0.3.0)
Requires-Dist: typer (>=0.12.3,<0.13.0)
